titan_mind/__init__.py
titan_mind/constants.py
titan_mind/networking.py
titan_mind/server.py
titan_mind/titan_mind_functions.py
titan_mind/utils/__init__.py
titan_mind/utils/app_specific/__init__.py
titan_mind/utils/app_specific/mcp.py
titan_mind/utils/app_specific/networking/__init__.py
titan_mind/utils/app_specific/networking/titan_mind.py
titan_mind/utils/app_specific/utils.py
titan_mind/utils/general/__init__.py
titan_mind/utils/general/date_time.py
titan_mind/utils/general/mcp.py
titan_mind/utils/general/networking.py
titan_mind_whatsapp_mcp-0.1.1.dist-info/METADATA
titan_mind_whatsapp_mcp-0.1.1.dist-info/WHEEL
titan_mind_whatsapp_mcp-0.1.1.dist-info/entry_points.txt
titan_mind_whatsapp_mcp-0.1.1.dist-info/RECORD
