Metadata-Version: 2.1
Name: titan-mind-whatsapp-mcp
Version: 0.1.1
Summary: MCP server for WhatsApp functionality via Titanmind
Author-Email: Shubhashish <shubhashish@salarybox.in>
Project-URL: Homepage, https://github.com/TitanmindAGI/titan-mind-whatsapp-mcp
Project-URL: Repository, https://github.com/TitanmindAGI/titan-mind-whatsapp-mcp
Requires-Python: >=3.10
Requires-Dist: fastmcp>=2.0.0
Requires-Dist: requests>=2.32.3
Requires-Dist: pydantic>=2.5.0
Requires-Dist: pydantic-core>=2.14.0
Requires-Dist: requests_oauthlib>=2.0.0
Requires-Dist: python-dotenv>=1.1.1
